mwg/__init__.py
mwg/markov_word_generator.py
mwg/dictionaries/DE-names.dic
mwg/dictionaries/DE-words.dic
mwg/dictionaries/EN-jobs.dic
mwg/dictionaries/EN-names.dic
mwg/dictionaries/EN-words.dic
mwg/dictionaries/ES-names.dic
mwg/dictionaries/ES-words.dic
mwg/dictionaries/FI-names.dic
mwg/dictionaries/FI-words.dic
mwg/dictionaries/FR-names.dic
mwg/dictionaries/FR-words.dic
mwg/dictionaries/IT-names.dic
mwg/dictionaries/IT-words.dic
mwg/dictionaries/PT-names.dic
mwg/dictionaries/PT-words.dic
mwg/dictionaries/SE-names.dic
mwg/dictionaries/SE-words.dic
mwg-0.5.2.dist-info/LICENSE
mwg-0.5.2.dist-info/METADATA
mwg-0.5.2.dist-info/WHEEL
mwg-0.5.2.dist-info/top_level.txt
mwg-0.5.2.dist-info/RECORD
