Metadata-Version: 2.1
Name: mwg
Version: 0.5.2
Summary: A small Python librairy to generate random credible words based on a list of words by esimating the probability of the next character from the frequency of the previous ones
Home-page: https://github.com/mariolpantunes/markov-word-generator
Author: Gaetan GOUZI
Author-email: gouzi.gaetan@gmail.com
Classifier: Programming Language :: Python :: 3
Classifier: License :: OSI Approved :: MIT License
Classifier: Operating System :: OS Independent
Requires-Python: >=3.9
License-File: LICENSE
Requires-Dist: Unidecode >=1.3.8
